machball/__init__.py
machball/aldmodels.py
machball/utils.py
machball/ballistic/__init__.py
machball/ballistic/ballistic.py
machball/ballistic/structure.py
machball/ballistic/viewfactors.py
machball-0.2.0.dist-info/LICENSE
machball-0.2.0.dist-info/METADATA
machball-0.2.0.dist-info/WHEEL
machball-0.2.0.dist-info/top_level.txt
machball-0.2.0.dist-info/RECORD
