Metadata-Version: 2.1
Name: machball
Version: 0.2.0
Summary: self-limited (ALD, ALE) reactive transport in nanostructures
Home-page: https://github.com/aldsim/machball
Author: Angel Yanguas-Gil
Author-email: ayg@anl.gov
License: UNKNOWN
Platform: UNKNOWN
Classifier: Programming Language :: Python :: 3
Classifier: License :: OSI Approved :: BSD License
Classifier: Operating System :: OS Independent
Classifier: Intended Audience :: Science/Research
Classifier: Intended Audience :: Manufacturing
Requires-Python: >=3.6
Requires-Dist: numpy
